Workbook

Sheet RAW DATA
A1: 🍎 RedFlagIQ — Apple Inc. (AAPL) | Raw Financial Data
A2: Source: Stockanalysis.com | Fiscal Year ends September | All figures in USD Millions
A3: Line Item | B3: FY2021 (Sep '21) | C3: FY2022 (Sep '22) | D3: FY2023 (Sep '23) | E3: FY2024 (Sep '24)
A4: INCOME STATEMENT
A5: Revenue | B5: 365817 | C5: 394328 | D5: 383285 | E5: 391035
A6: Cost of Revenue (COGS) | B6: 212981 | C6: 223546 | D6: 214137 | E6: 210352
A7: Gross Profit | B7: =B5-B6 -> 152836 | C7: =C5-C6 -> 170782 | D7: =D5-D6 -> 169148 | E7: =E5-E6 -> 180683
A8: SG&A Expenses | B8: 21973 | C8: 25094 | D8: 24932 | E8: 26097
A9: Depreciation & Amortisation | B9: 11284 | C9: 11104 | D9: 11519 | E9: 11445
A10: EBIT (Operating Income) | B10: 108949 | C10: 119437 | D10: 114301 | E10: 123216
A11: Net Income | B11: 94680 | C11: 99803 | D11: 96995 | E11: 93736
A12: BALANCE SHEET
A13: Total Assets | B13: 351002 | C13: 352755 | D13: 352583 | E13: 364980
A14: Current Assets | B14: 134836 | C14: 135405 | D14: 143566 | E14: 152987
A15: Current Liabilities | B15: 125481 | C15: 153982 | D15: 145308 | E15: 176392
A16: Accounts Receivable | B16: 26278 | C16: 28184 | D16: 29508 | E16: 33410
A17: Long Term Debt | B17: 109106 | C17: 98959 | D17: 95281 | E17: 85750
A18: Total Liabilities | B18: 287912 | C18: 302083 | D18: 290437 | E18: 308030
A19: Retained Earnings | B19: 5562 | C19: -3068 | D19: -214 | E19: -19154
A20: Market Capitalisation | B20: 2580000 | C20: 2067000 | D20: 2993000 | E20: 3500000
A21: CASH FLOW STATEMENT
A22: Operating Cash Flow (OCF) | B22: 104038 | C22: 122151 | D22: 110543 | E22: 118254
A23: Capital Expenditure | B23: 11085 | C23: 10708 | D23: 10959 | E23: 9447
A24: Free Cash Flow (FCF) | B24: =B22-B23 -> 92953 | C24: =C22-C23 -> 111443 | D24: =D22-D23 -> 99584 | E24: =E22-E23 -> 108807
A27: 🔵 Blue text = Hardcoded inputs (you type these in) | C27: ⚫ Black text = Calculated by formula
A28: 🟡 Yellow = Cells that need your attention | C28: 🟢 Green text = Pulled from another sheet

Sheet BENEISH M-SCORE
A1: 🚨 Beneish M-Score | Earnings Manipulation Detector
A2: Score > -1.78 signals likely earnings manipulation | Comparing FY2023 (Prior Year) vs FY2024 (Current Year)
A3: Ratio | B3: What It Checks | C3: Prior Year (FY2023) | D3: Current Year (FY2024) | E3: Calculated Value | F3: Red Flag?
A4: 1. DSRI Days Sales Receivable Index | B4: Are receivables growing faster than sales? High = possible fake revenue | C4: ='RAW DATA'!D16/'RAW DATA'!D5 -> 0.076987098 | D4: ='RAW DATA'!E16/'RAW DATA'!E5 -> 0.085439922 | E4: =D5/C5 -> 1.047024 | F4: =IF(E4>1.031,"🔴 FLAG","✅ OK") -> 🔴 FLAG
A5: 2. GMI Gross Margin Index | B5: Is gross margin shrinking? Shrinking margins = pressure to manipulate | C5: =('RAW DATA'!D5-'RAW DATA'!D6)/'RAW DATA'!D5 -> 0.4413113 | D5: =('RAW DATA'!E5-'RAW DATA'!E6)/'RAW DATA'!E5 -> 0.4620635 | E5: =C6/D6 -> 1.0426652 | F5: =IF(E5>1.014,"🔴 FLAG","✅ OK") -> 🔴 FLAG
A6: 3. AQI Asset Quality Index | B6: https://d.docs.live.net/A630F44E73B8FF02/Documents/REFFLAG%20IQ.xlsx | C6: =1-(('RAW DATA'!D14+'RAW DATA'!D13*0.3)/'RAW DATA'!D13) -> 0.29281644 | D6: =1-(('RAW DATA'!E14+'RAW DATA'!E13*0.3)/'RAW DATA'!E13) -> 0.28083457 | E6: =D7/C7 -> 1.0202199 | F6: =IF(E6>1.04,"🔴 FLAG","✅ OK") -> ✅ OK
A7: 4. SGI Sales Growth Index | B7: Is sales growth very high? High growth = pressure to sustain it | C7: ='RAW DATA'!D5 -> 383285 | D7: ='RAW DATA'!E5 -> 391035 | E7: =D8/C8 -> 0.98067133 | F7: =IF(E7>1.134,"🔴 FLAG","✅ OK") -> ✅ OK
A8: 5. DEPI Depreciation Index | B8: Is depreciation slowing down? Slowing = inflating assets artificially | C8: ='RAW DATA'!D9/('RAW DATA'!D9+('RAW DATA'!D13-'RAW DATA'!D14)) -> 0.052231835 | D8: ='RAW DATA'!E9/('RAW DATA'!E9+('RAW DATA'!E13-'RAW DATA'!E14)) -> 0.051222263 | E8: =C9/D9 -> 0.97467615 | F8: =IF(E8>1.001,"🔴 FLAG","✅ OK") -> ✅ OK
A9: 6. SGAI SGA Expense Index | B9: Are overheads growing faster than sales? High = operational inefficiency | C9: ='RAW DATA'!D8/'RAW DATA'!D5 -> 0.065048202 | D9: ='RAW DATA'!E8/'RAW DATA'!E5 -> 0.066738272 | E9: =D10/C10 -> 1.0525752 | F9: =IF(E9>1.054,"🔴 FLAG","✅ OK") -> ✅ OK
A10: 7. LVGI Leverage Index | B10: Is the company taking on more debt? More debt = more pressure = higher risk | C10: =('RAW DATA'!D17+'RAW DATA'!D15)/'RAW DATA'!D13 -> 0.68236132 | D10: =('RAW DATA'!E17+'RAW DATA'!E15)/'RAW DATA'!E13 -> 0.71823662 | E10: =D10/C10 -> 1.0525752 | F10: =IF(E10>1.111,"🔴 FLAG","✅ OK") -> ✅ OK
A11: 8. TATA Total Accruals to Total Assets | B11: Are earnings backed by real cash? High = paper profits, not real cash | C11: N/A (only current year needed) | D11: =('RAW DATA'!E11-'RAW DATA'!E22)/'RAW DATA'!E13 -> -0.067176284 | E11: =D11 -> -0.067176284 | F11: =IF(E11>0.018,"🔴 FLAG","✅ OK") -> ✅ OK
A13: M-SCORE FORMULA: = -4.84 + (0.920×DSRI) + (0.528×GMI) + (0.404×AQI) + (0.892×SGI) + (0.115×DEPI) - (0.172×SGAI) - (0.327×TATA) + (4.679×LVGI)
A14: Final M-Score | E14: =-4.84+(0.92*E4)+(0.528*E5)+(0.404*E6)+(0.892*E7)+(0.115*E8)-(0.172*E9)+(4.679*E10)-(0.327*E11) -> 2.8387279
A15: Interpretation | E15: =IF(E14>-1.78,"🔴 LIKELY MANIPULATOR",IF(E14>-2.22,"🟡 GREY ZONE — Monitor","🟢 UNLIKELY MANIPULATOR")) -> 🔴 LIKELY MANIPULATOR

Sheet ALTMAN Z-SCORE
A1: 📊 Altman Z-Score | Bankruptcy & Financial Distress Predictor
A2: Z > 2.99 = Safe | 1.81–2.99 = Grey Zone | < 1.81 = Distress | Using FY2024 data
A3: Factor | B3: What It Measures | C3: Formula / Value | D3: Weight | E3: Weighted Value | F3: Interpretation
A4: X1 — Working Capital / Total Assets | B4: Short-term financial cushion. Negative = can't cover short-term bills | C4: =('RAW DATA'!E14-'RAW DATA'!E15)/'RAW DATA'!E13 -> -0.064126801 | D4: 1.2 | E4: =C4*D4 -> -0.076952162 | F4: Liquidity buffer
A5: X2 — Retained Earnings / Total Assets | B5: Cumulative profitability. Negative for Apple = massive buybacks | C5: ='RAW DATA'!E19/'RAW DATA'!E13 -> -0.052479588 | D5: 1.4 | E5: =C5*D5 -> -0.073471423 | F5: Long-term profitability
A6: X3 — EBIT / Total Assets | B6: How well assets generate operating profit. Higher = more efficient | C6: ='RAW DATA'!E10/'RAW DATA'!E13 -> 0.33759658 | D6: 3.3 | E6: =C6*D6 -> 1.1140687 | F6: Operating efficiency
A7: X4 — Market Cap / Total Liabilities | B7: Can market value cover all debts? Very high for Apple = safe | C7: ='RAW DATA'!E20/'RAW DATA'!E18 -> 11.36253 | D7: 0.6 | E7: =C7*D7 -> 6.8175178 | F7: Market-based solvency
A8: X5 — Revenue / Total Assets | B8: Asset turnover efficiency. How much revenue per dollar of assets | C8: ='RAW DATA'!E5/'RAW DATA'!E13 -> 1.0713875 | D8: 1 | E8: =C8*D8 -> 1.0713875 | F8: Asset efficiency
A10: Final Z-Score | E10: =SUM(E4:E8) -> 8.8525504
A11: Zone | E11: =IF(E10>2.99,"🟢 SAFE ZONE — No distress signal",IF(E10>1.81,"🟡 GREY ZONE — Monitor closely","🔴 DISTRESS ZONE — High bankruptcy risk")) -> 🟢 SAFE ZONE — No distress signal
A13: QUICK REFERENCE
A14: Z > 2.99 | B14: Safe Zone | C14: Low probability of bankruptcy
A15: 1.81 – 2.99 | B15: Grey Zone | C15: Uncertain — monitor financial health
A16: < 1.81 | B16: Distress Zone | C16: High probability of financial distress

Sheet RED FLAGS
A1: 🔍 Custom Red Flag Checklist | Apple Inc. (AAPL) | FY2023 vs FY2024
A2: Beyond Beneish & Altman — additional heuristic red flags for fundamental analysis
A3: # | B3: Red Flag | C3: What to Check | D3: FY2023 Value | E3: FY2024 Value | F3: Status
A4: 1 | B4: Revenue growing but OCF flat or declining | C4: Revenue growth > 10% AND OCF growth < 2% → Earnings not backed by cash | D4: ='RAW DATA'!D5 -> 383285 | E4: ='RAW DATA'!E5 -> 391035 | F4: =IF(AND((E4-D4)/D4>0.1,('[1]Raw Data'!E22-'[1]Raw Data'!D22)/'[1]Raw Data'!D22<0.02),"🔴 FLAG","✅ OK") -> ✅ OK
A5: 2 | B5: Receivables growing 2x faster than Revenue | C5: AR growth > 2 × Revenue growth → Possible fake or uncollected sales | D5: ='RAW DATA'!D16 -> 29508 | E5: ='RAW DATA'!E16 -> 33410 | F5: =IF((E5-D5)/D5>(2*('[1]Raw Data'!E5-'[1]Raw Data'!D5)/'[1]Raw Data'!D5),"🔴 FLAG","✅ OK") -> 🔴 FLAG
A6: 3 | B6: Gross Margin declining 2 consecutive years | C6: GM shrinking YoY for 2+ years → Core business under pressure | D6: =('RAW DATA'!D5-'RAW DATA'!D6)/'RAW DATA'!D5 -> 0.4413113 | E6: =('RAW DATA'!E5-'RAW DATA'!E6)/'RAW DATA'!E5 -> 0.4620635 | F6: =IF(E6<D6,"🔴 FLAG — Margin declined","✅ OK — Margin stable or improving") -> ✅ OK — Margin stable or improving
A7: 4 | B7: Debt-to-Equity spike > 40% in one year | C7: D/E ratio jumped > 40% YoY → Rapid leverage increase = higher risk | D7: ='RAW DATA'!D17/('RAW DATA'!D13-'RAW DATA'!D18) -> 1.5331799 | E7: ='RAW DATA'!E17/('RAW DATA'!E13-'RAW DATA'!E18) -> 1.5057068 | F7: =IF(ABS((E7-D7)/D7)>0.4,"🔴 FLAG","✅ OK") -> ✅ OK
A8: 5 | B8: Net Income positive but FCF negative | C8: NI > 0 AND FCF < 0 → Profits on paper but no real cash | D8: ='RAW DATA'!D11 -> 96995 | E8: ='RAW DATA'!E11 -> 93736 | F8: =IF(AND(E8>0,'[1]Raw Data'!E24<0),"🔴 FLAG — Paper profits only","✅ OK — Cash backed") -> ✅ OK — Cash backed
A10: Total Red Flags Triggered | F10: =COUNTIF(F4:F8,"🔴 FLAG") -> 1

Sheet FINAL REPORT
A1: RedFlagIQ — Company Risk Report
A2: Automated Financial Statement Analysis | Forensic Finance Framework
A3: Company Name | B3: Apple Inc.
A4: Ticker | B4: AAPL
A5: Exchange | B5: NASDAQ
A6: Analysis Year | B6: FY2024 (Sep 2024)
A7: Report Date | B7: 2024
A9: SCORING RESULTS
A10: Beneish M-Score | B10: {='BENEISH M-SCORE'!E14:F14} -> 2.8387279 | C10: 0
A11: M-Score Verdict | B11: {='BENEISH M-SCORE'!E15:F15} -> 🔴 LIKELY MANIPULATOR | C11: 0
A12: Altman Z-Score | B12: {='ALTMAN Z-SCORE'!E10:F10} -> 8.8525504 | C12: 0
A13: Z-Score Zone | B13: {='ALTMAN Z-SCORE'!E11:F11} -> 🟢 SAFE ZONE — No distress signal | C13: 0
A14: Custom Flags Triggered | B14: ='RED FLAGS'!F10 -> 1
A16: OVERALL RISK RATING
A17: Risk Rating | B17: =IF(OR('[1]Beneish M-Score'!E14>-1.78,'[1]Altman Z-Score'!E10<1.81,'[1]Custom Red Flags'!F10>=4),"🔴 HIGH RISK",IF(OR('[1]Beneish M-Score'!E14>-2.22,'[1]Altman Z-Score'!E10<2.99,'[1]Custom Red Flags'!F10>=2),"🟡 MEDIUM RISK","🟢 LOW RISK")) -> 🔴 HIGH RISK
A19: ANALYST NOTES
A20: Key Finding 1 | B20: Receivables growing faster than revenue — monitor AR trends
A21: Key Finding 2 | B21: M-Score in grey zone — driven by DSRI and LVGI ratios
A22: Key Finding 3 | B22: Negative retained earnings = buyback programme, not losses
A23: Key Finding 4 | B23: Z-Score of ~8.9 — zero financial distress risk
A24: Conclusion | B24: Overall LOW risk. Apple financials are healthy. DSRI warrants monitoring.
A26: ⚠️ DISCLAIMER: This model is for educational and portfolio purposes only. Not financial advice.
